README.md
setup.py
./Flask_PonyManager.egg-info/PKG-INFO
./Flask_PonyManager.egg-info/SOURCES.txt
./Flask_PonyManager.egg-info/dependency_links.txt
./Flask_PonyManager.egg-info/not-zip-safe
./Flask_PonyManager.egg-info/requires.txt
./Flask_PonyManager.egg-info/top_level.txt
./flask_ponymanager/__init__.py
./flask_ponymanager/former.py
./flask_ponymanager/ponymanager.py
./flask_ponymanager/view.py
Flask_PonyManager.egg-info/PKG-INFO
Flask_PonyManager.egg-info/SOURCES.txt
Flask_PonyManager.egg-info/dependency_links.txt
Flask_PonyManager.egg-info/not-zip-safe
Flask_PonyManager.egg-info/requires.txt
Flask_PonyManager.egg-info/top_level.txt
flask_ponymanager/__init__.py
flask_ponymanager/former.py
flask_ponymanager/ponymanager.py
flask_ponymanager/view.py