Metadata-Version: 2.1
Name: Flask-PonyManager
Version: 3.0
Summary: Similar to Flask-Admin but for Pony ORM.
Home-page: https://tlasky@bitbucket.org/tlasky/flaskponymanager
Author: David Tláskal
Author-email: da.tlaskal@gmail.com
License: BSD
Platform: any
Classifier: Environment :: Web Environment
Classifier: Intended Audience :: Developers
Classifier: License :: OSI Approved :: BSD License
Classifier: Operating System :: OS Independent
Classifier: Programming Language :: Python
Classifier: Topic :: Internet :: WWW/HTTP :: Dynamic Content
Classifier: Topic :: Software Development :: Libraries :: Python Modules
